pagedlist/pagedlist.py
pagedlist/__init__.py
pagedlist/web/builder.py
pagedlist/web/options.py
pagedlist/web/__init__.py
pagedlist/web/ajax/options.py
pagedlist/web/ajax/__init__.py
pypagedlist-0.2.3.dist-info/DESCRIPTION.rst
pypagedlist-0.2.3.dist-info/METADATA
pypagedlist-0.2.3.dist-info/metadata.json
pypagedlist-0.2.3.dist-info/RECORD
pypagedlist-0.2.3.dist-info/top_level.txt
pypagedlist-0.2.3.dist-info/WHEEL
